tc_queue_system/__init__.py
tc_queue_system/service.py
tc_queue_system-1.0.0.dist-info/licenses/LICENSE
tc_queue_system-1.0.0.dist-info/METADATA
tc_queue_system-1.0.0.dist-info/WHEEL
tc_queue_system-1.0.0.dist-info/entry_points.txt
tc_queue_system-1.0.0.dist-info/top_level.txt
tc_queue_system-1.0.0.dist-info/RECORD
