Metadata-Version: 2.4
Name: tc-queue-system
Version: 1.0.0
Summary: A flexible message queue system with SQLite backend and Flask API
Home-page: https://github.com/task-circuit/tc-queue-system
Author: Yashvanth D
Author-email: Yashvanth D <dev@taskcircuit.com>
License: MIT
Project-URL: Homepage, https://github.com/task-circuit/tc-queue-system
Project-URL: Documentation, https://github.com/task-circuit/tc-queue-system#readme
Project-URL: Repository, https://github.com/task-circuit/tc-queue-system
Project-URL: Bug Tracker, https://github.com/task-circuit/tc-queue-system/issues
Keywords: queue,message-queue,task-queue,sqlite,flask-api
Classifier: Development Status :: 4 - Beta
Classifier: Intended Audience :: Developers
Classifier: License :: OSI Approved :: MIT License
Classifier: Operating System :: OS Independent
Classifier: Programming Language :: Python :: 3
Classifier: Programming Language :: Python :: 3.8
Classifier: Programming Language :: Python :: 3.9
Classifier: Programming Language :: Python :: 3.10
Classifier: Programming Language :: Python :: 3.11
Classifier: Programming Language :: Python :: 3.12
Classifier: Topic :: Software Development :: Libraries :: Python Modules
Classifier: Topic :: System :: Distributed Computing
Requires-Python: >=3.8
License-File: LICENSE
Provides-Extra: dev
Requires-Dist: pytest>=7.0.0; extra == "dev"
Requires-Dist: pytest-cov>=4.0.0; extra == "dev"
Requires-Dist: black>=23.0.0; extra == "dev"
Requires-Dist: flake8>=6.0.0; extra == "dev"
Requires-Dist: mypy>=1.0.0; extra == "dev"
Provides-Extra: server
Requires-Dist: flask>=2.0.0; extra == "server"
Provides-Extra: all
Requires-Dist: flask>=2.0.0; extra == "all"
Dynamic: author
Dynamic: home-page
Dynamic: license-file
Dynamic: requires-python
